__init__.py
gtoolz.py
gtoolz-0.1.5.dist-info/LICENSE
gtoolz-0.1.5.dist-info/METADATA
gtoolz-0.1.5.dist-info/WHEEL
gtoolz-0.1.5.dist-info/entry_points.txt
gtoolz-0.1.5.dist-info/top_level.txt
gtoolz-0.1.5.dist-info/RECORD
