Metadata-Version: 2.1
Name: gtoolz
Version: 0.1.5
Summary: This package provides a multitude of functions or classes to manipulate data into ascii color tables or build dashboards
Author-email: Geoff McNamara <geoff.mcnamara@gmail.com>
Project-URL: Homepage, https://github.com/geoffmcnamara/gtoolz
Project-URL: Bug Trakers, https://github.com/geoffmcnamara/gtoolz/issues
Classifier: Programming Language :: Python :: 3
Classifier: License :: OSI Approved :: MIT License
Classifier: Environment :: Console
Classifier: Operating System :: POSIX :: Linux
Requires-Python: >=3.7
License-File: LICENSE
Requires-Dist: docopt
Requires-Dist: pandas
